democritus/__init__.py
democritus/democritus.py
democritus-2020.8.19.dist-info/LICENSE
democritus-2020.8.19.dist-info/METADATA
democritus-2020.8.19.dist-info/WHEEL
democritus-2020.8.19.dist-info/top_level.txt
democritus-2020.8.19.dist-info/zip-safe
democritus-2020.8.19.dist-info/RECORD
