Metadata-Version: 2.1
Name: democritus
Version: 2020.8.19
Summary: Future home of democritus project.
Home-page: https://gitlab.com/fhightower/democritus
Author: Floyd Hightower
Author-email: floyd.hightower27@gmail.com
License: MIT License
